workaround/__init__.py
workaround/cli.py
workaround/handle.py
workaround/handlers/__init__.py
workaround/handlers/base.py
workaround/handlers/django.py
workaround/handlers/github.py
workaround/handlers/npm.py
workaround/handlers/pypi.py
workaround-0.1.1.dist-info/DESCRIPTION.rst
workaround-0.1.1.dist-info/METADATA
workaround-0.1.1.dist-info/RECORD
workaround-0.1.1.dist-info/WHEEL
workaround-0.1.1.dist-info/entry_points.txt
workaround-0.1.1.dist-info/metadata.json
workaround-0.1.1.dist-info/top_level.txt
